zadanhie 6/msb_8bit.v
module msb_8bit(
    input clk,
    input [7:0] input_num,
    output reg [3:0] output_pos
);

integer i;
integer flag ;
always @(posedge clk)begin
    flag = 0;
    output_pos = 4'd0;
    i = 7;
    while (i >= 0 && flag == 0) begin
        if (input_num[i] == 1'b1) begin
            output_pos =  i +1;
            flag = 1;
        end 
        i = i - 1;
    end
end

endmodule;

zadanhie 6/msb_32bit.v
`include "msb_8bit.v"

//a) вход 32 бита
module msb_32bit(
    input clk,
    input [31:0] input_num,
    output reg [5:0] output_pos
);

integer i;
integer flag ;
wire [7:0] input_part [3:0];
wire [3:0] part_msb [3:0];

assign input_part[0] = input_num[7:0];
assign input_part[1] = input_num[15:8];
assign input_part[2] = input_num[23:16];
assign input_part[3] = input_num[31:24];

msb_8bit msb_8bit_0(.input_num(input_part[0]),.output_pos(part_msb[0]), .clk(clk));
msb_8bit msb_8bit_1(.input_num(input_part[1]),.output_pos(part_msb[1]),.clk(clk));
msb_8bit msb_8bit_2(.input_num(input_part[2]),.output_pos(part_msb[2]),.clk(clk));
msb_8bit msb_8bit_3(.input_num(input_part[3]),.output_pos(part_msb[3]),.clk(clk));

always @(posedge clk)begin
    flag = 0;
    output_pos = 6'd0;
    i = 3;
    while (i >= 0 && flag == 0) begin
        if(part_msb[i]!=4'b0) begin
            output_pos = (i*8) + part_msb[i];
            flag =1;
        end
        i = i-1;

    end

end

endmodule

zadanhie 6/msb_32bit_tb.v
`timescale 1ns/1ns
`include "msb_32bit.v"
module msb_tb();

reg clk =1;
initial
    forever 
        #5 clk = ~clk;
reg [31:0] input_num;
wire [5:0] output_pos;

msb_32bit msb_32bit (
    .clk(clk),
    .input_num(input_num),
    .output_pos(output_pos)
);

initial 
begin
    $dumpfile("dump_32bit.vcd");
    $dumpvars(0,msb_tb);
    
end;

initial begin
    #10
    input_num = 32'h31003131;
    #20;
    input_num = 32'h00003131;
    #20;
    input_num = 32'h00000001;
    #20;
    $finish();
end

endmodule;

zadanhie 6/dump_32bit.vcd
$date
	Tue May 09 17:59:58 2023
$end
$version
	Icarus Verilog
$end
$timescale
	1ns
$end
$scope module msb_tb $end
$var wire 6 ! output_pos [5:0] $end
$var reg 1 " clk $end
$var reg 32 # input_num [31:0] $end
$scope module msb_32bit $end
$var wire 1 " clk $end
$var wire 32 $ input_num [31:0] $end
$var reg 6 % output_pos [5:0] $end
$var integer 32 & flag [31:0] $end
$var integer 32 ' i [31:0] $end
$scope module msb_8bit_0 $end
$var wire 1 " clk $end
$var wire 8 ( input_num [7:0] $end
$var reg 4 ) output_pos [3:0] $end
$var integer 32 * flag [31:0] $end
$var integer 32 + i [31:0] $end
$upscope $end
$scope module msb_8bit_1 $end
$var wire 1 " clk $end
$var wire 8 , input_num [7:0] $end
$var reg 4 - output_pos [3:0] $end
$var integer 32 . flag [31:0] $end
$var integer 32 / i [31:0] $end
$upscope $end
$scope module msb_8bit_2 $end
$var wire 1 " clk $end
$var wire 8 0 input_num [7:0] $end
$var reg 4 1 output_pos [3:0] $end
$var integer 32 2 flag [31:0] $end
$var integer 32 3 i [31:0] $end
$upscope $end
$scope module msb_8bit_3 $end
$var wire 1 " clk $end
$var wire 8 4 input_num [7:0] $end
$var reg 4 5 output_pos [3:0] $end
$var integer 32 6 flag [31:0] $end
$var integer 32 7 i [31:0] $end
$upscope $end
$upscope $end
$upscope $end
$enddefinitions $end
$comment Show the parameter values. $end
$dumpall
$end
#0
$dumpvars
b11111111111111111111111111111111 7
b0 6
b0 5
bx 4
b11111111111111111111111111111111 3
b0 2
b0 1
bx 0
b11111111111111111111111111111111 /
b0 .
b0 -
bx ,
b11111111111111111111111111111111 +
b0 *
b0 )
bx (
b11111111111111111111111111111111 '
b0 &
b0 %
bx $
bx #
1"
b0 !
$end
#5
0"
#10
b1 &
b11110 !
b11110 %
b10 '
b1 6
b110 5
b100 7
b11111111111111111111111111111111 3
b1 .
b110 -
b100 /
b1 *
b110 )
b100 +
b110001 (
b110001 ,
b0 0
b110001 4
1"
b110001000000000011000100110001 #
b110001000000000011000100110001 $
#15
0"
#20
b100 +
b110 )
b1 *
b100 /
b110 -
b1 .
b11111111111111111111111111111111 3
b100 7
b110 5
b1 6
b10 '
b11110 !
b11110 %
b1 &
1"
#25
0"
#30
b0 '
b1110 !
b1110 %
b1 &
b11111111111111111111111111111111 7
b0 5
b0 6
b11111111111111111111111111111111 3
b100 /
b110 -
b1 .
b100 +
b110 )
b1 *
b0 4
1"
b11000100110001 #
b11000100110001 $
#35
0"
#40
b100 +
b110 )
b1 *
b100 /
b110 -
b1 .
b11111111111111111111111111111111 3
b11111111111111111111111111111111 7
b0 '
b1110 !
b1110 %
b1 &
1"
#45
0"
#50
b11111111111111111111111111111111 '
b1 !
b1 %
b1 &
b11111111111111111111111111111111 7
b11111111111111111111111111111111 3
b11111111111111111111111111111111 /
b0 -
b0 .
b11111111111111111111111111111111 +
b1 )
b1 *
b1 (
b0 ,
1"
b1 #
b1 $
#55
0"
#60
b11111111111111111111111111111111 +
b1 )
b1 *
b11111111111111111111111111111111 /
b11111111111111111111111111111111 3
b11111111111111111111111111111111 7
b11111111111111111111111111111111 '
b1 !
b1 %
b1 &
1"
#65
0"
#70
b11111111111111111111111111111111 '
b1 !
b1 %
b1 &
b11111111111111111111111111111111 7
b11111111111111111111111111111111 3
b11111111111111111111111111111111 /
b11111111111111111111111111111111 +
b1 )
b1 *
1"
